koreui/__init__.py
koreui/kore.py
koreui/loader.py
koreui-0.4.1.dist-info/licenses/LICENSE
koreui-0.4.1.dist-info/METADATA
koreui-0.4.1.dist-info/WHEEL
koreui-0.4.1.dist-info/top_level.txt
koreui-0.4.1.dist-info/RECORD
