Metadata-Version: 2.4
Name: koreui
Version: 0.4.1
Summary: Dynamic GUI Generator from JSON Schema
Author-email: TheJupiterDev <thatgeometrydude@gmail.com>
License: AGPL-3.0-only
Project-URL: Homepage, https://github.com/TheJupiterDev/KoreUI
Project-URL: Repository, https://github.com/TheJupiterDev/KoreUI.git
Requires-Python: >=3.10
License-File: LICENSE
Requires-Dist: PySide6>=6.9.0
Dynamic: license-file
